setup.py
account/__init__.py
account/forms.py
account/models.py
account/tests.py
account/views.py
django_googleplus.egg-info/PKG-INFO
django_googleplus.egg-info/SOURCES.txt
django_googleplus.egg-info/dependency_links.txt
django_googleplus.egg-info/top_level.txt
googleplus/__init__.py
googleplus/forms.py
googleplus/models.py
googleplus/tests.py
googleplus/urls.py
googleplus/utils.py
googleplus/views.py
googleplus/backends/__init__.py
googleplus/backends/default/__init__.py