Metadata-Version: 1.0
Name: django-googleplus
Version: 0.1
Summary:  A plugable registration backend for googleplus. Closely modeled after django-registration
Home-page: https://github.com/jonasgeiregat/django-googleplus
Author: Jonas Geiregat
Author-email: jonas@geiregat.org
License: UNKNOWN
Platform: UNKNOWN
